valar/__init__.py
valar/apps.py
valar/urls.py
valar/auth/Authentication.py
valar/auth/Middleware.py
valar/auth/__init__.py
valar/channels/__init__.py
valar/channels/consumer.py
valar/channels/counter.py
valar/channels/executer.py
valar/channels/mapping.py
valar/channels/sender.py
valar/channels/views.py
valar/classes/__init__.py
valar/classes/singleton_meta.py
valar/classes/valar_minio.py
valar/classes/valar_response.py
valar/classes/app_mixins/__init__.py
valar/classes/app_mixins/auto_migration_mixin.py
valar/classes/app_mixins/auto_urlpatterns_mixin.py
valar/dao/__init__.py
valar/dao/abstract.py
valar/dao/engine.py
valar/dao/frame.py
valar/dao/meta.py
valar/dao/mon_dao.py
valar/dao/mon_field.py
valar/dao/orm_dao.py
valar/dao/orm_field.py
valar/dao/query.py
valar/dao/defaults/__init__.py
valar/dao/defaults/field_keys_default.py
valar/dao/defaults/field_values_default.py
valar/dao/defaults/view_defaults.py
valar/migrations/__init__.py
valar/models/__init__.py
valar/models/auth.py
valar/models/core.py
valar/models/frame.py
valar/models/indicator.py
valar/models/meta.py
valar/models/test.py
valar/views/__init__.py
valar/views/auth.py
valar/views/file.py
valar/views/handler.py
valar/views/meta.py
valar/views/password.py
valar/views/rest.py
valar-1.3.28.dist-info/licenses/LICENSE
valar-1.3.28.dist-info/METADATA
valar-1.3.28.dist-info/WHEEL
valar-1.3.28.dist-info/top_level.txt
valar-1.3.28.dist-info/RECORD
