Metadata-Version: 2.4
Name: valar
Version: 1.3.28
Summary: valar for morghulis
Home-page: https://gitee.com/GRIFFIN120/valar_dev
Author: LYP
Author-email: liuyinpeng@buaa.edu.cn
Requires-Python: >=3.9
License-File: LICENSE
Requires-Dist: autobahn==24.4.2
Requires-Dist: channels==3.0.3
Requires-Dist: pymongo~=4.11.2
Requires-Dist: asgiref~=3.8.1
Requires-Dist: django-cors-headers==4.2.0
Requires-Dist: pandas==2.2.3
Requires-Dist: openpyxl==3.1.5
Requires-Dist: deepmerge~=2.0
Requires-Dist: minio==7.2.2
Requires-Dist: PyJWT~=2.10.1
Requires-Dist: PyMySQL~=1.1.2
Dynamic: author
Dynamic: author-email
Dynamic: description
Dynamic: description-content-type
Dynamic: home-page
Dynamic: license-file
Dynamic: requires-dist
Dynamic: requires-python
Dynamic: summary
